resolveit/__init__.py
resolveit/column_stats.py
resolveit/column_stats_numeric.py
resolveit/column_vectors.py
resolveit/files.py
resolveit/get_all_stats.py
resolveit/get_column_stats.py
resolveit/shingle.py
resolveit/show_matrix.py
resolveit/utils.py
resolveit-0.1.3.dist-info/LICENSE.txt
resolveit-0.1.3.dist-info/METADATA
resolveit-0.1.3.dist-info/WHEEL
resolveit-0.1.3.dist-info/top_level.txt
resolveit-0.1.3.dist-info/RECORD
